setup.py
distributed_prob/Binomialdistribution.py
distributed_prob/Gaussiandistribution.py
distributed_prob/Generaldistribution.py
distributed_prob/__init__.py
distributed_prob.egg-info/PKG-INFO
distributed_prob.egg-info/SOURCES.txt
distributed_prob.egg-info/dependency_links.txt
distributed_prob.egg-info/not-zip-safe
distributed_prob.egg-info/top_level.txt