Metadata-Version: 1.0
Name: distributed-prob
Version: 1.0
Summary: Gaussian and Binomial distributions
Home-page: UNKNOWN
Author: Prerna Singh
Author-email: writeprernasingh@gmail.com
License: UNKNOWN
Platform: UNKNOWN
